souswift_core/__init__.py
souswift_core/exc/__init__.py
souswift_core/exc/exceptions.py
souswift_core/exc/ext.py
souswift_core/exc/handlers.py
souswift_core/filters/__init__.py
souswift_core/filters/base.py
souswift_core/filters/comp.py
souswift_core/filters/cp.py
souswift_core/filters/paginator.py
souswift_core/filters/where.py
souswift_core/finder.py
souswift_core/future/__init__.py
souswift_core/future/providers/__init__.py
souswift_core/future/providers/config.py
souswift_core/models.py
souswift_core/providers/__init__.py
souswift_core/providers/config.py
souswift_core/providers/database.py
souswift_core/py.typed
souswift_core/utils/__init__.py
souswift_core/utils/helpers.py
souswift_core/utils/string.py
souswift_core/utils/timezone.py
souswift_core-3.1.1.dist-info/WHEEL
souswift_core-3.1.1.dist-info/METADATA
souswift_core-3.1.1.dist-info/RECORD
