Metadata-Version: 2.1
Name: souswift-core
Version: 3.1.1
Summary: 
Author: Gustavo Correa
Author-email: self.gustavocorrea@gmail.com
Requires-Python: >=3.10,<4.0
Classifier: Programming Language :: Python :: 3
Classifier: Programming Language :: Python :: 3.10
Classifier: Programming Language :: Python :: 3.11
Requires-Dist: SQLAlchemy (>=1.4.41,<2.0.0)
Requires-Dist: aiomysql (>=0.1.1,<0.2.0)
Requires-Dist: context-handler (>=5.1.0,<6.0.0)
Requires-Dist: fastapi (>=0.85.0,<0.86.0)
Requires-Dist: orjson (>=3.8.0,<4.0.0)
Requires-Dist: pydantic[email] (>=1.10.2,<2.0.0)
Requires-Dist: tzdata (>=2022.4,<2023.0)
